datapeachcli.py
datapeach-1.0.1.dist-info/METADATA
datapeach-1.0.1.dist-info/WHEEL
datapeach-1.0.1.dist-info/entry_points.txt
datapeach-1.0.1.dist-info/top_level.txt
datapeach-1.0.1.dist-info/RECORD
